{
  "headers": {
    "server-timing": "fetchSource;dur=6",
    "accept-ranges": "bytes",
    "cross-origin-resource-policy": "same-origin",
    "x-amz-version-id": "05BACw3SQvKe7Paqq2.Ls9YdpT6.W_Tk",
    "content-security-policy": "default-src 'none'; style-src 'unsafe-inline'; sandbox",
    "content-length": "453",
    "strict-transport-security": "max-age=63072000; includeSubDomains; preload",
    "x-cache": "Hit from cloudfront",
    "cross-origin-embedder-policy": "same-origin",
    "last-modified": "Wed, 27 Sep 2023 04:05:42 GMT",
    "x-amz-cf-id": "MLc1oITPIKRznmflIHjccWgwEh1mw1KvfpqAS7vSOfMdplkUYRWhEg==",
    "etag": "\"ba578513c676d45e1e3a82f2548ad55a\"",
    "cache-control": "public, max-age=31536000, immutable",
    "x-frame-options": "DENY",
    "content-type": "application/typescript; charset=utf-8",
    "server": "deno/gcp-europe-west8",
    "x-amz-cf-pop": "MXP53-P1",
    "x-amz-server-side-encryption": "AES256",
    "x-content-type-options": "nosniff",
    "date": "Wed, 27 Sep 2023 04:05:56 GMT",
    "age": "1227575",
    "x-amz-replication-status": "PENDING",
    "cross-origin-opener-policy": "same-origin",
    "access-control-allow-origin": "*",
    "via": "http/2 edgeproxy-h",
    "vary": "Accept-Encoding, Origin",
    "referrer-policy": "strict-origin-when-cross-origin"
  },
  "url": "https://deno.land/std@0.203.0/path/parse.ts",
  "now": {
    "secs_since_epoch": 1697015131,
    "nanos_since_epoch": 190141268
  }
}